vicroads_transport_api/__init__.py
vicroads_transport_api/client.py
vicroads_transport_api/errors.py
vicroads_transport_api/gtfs_model.py
vicroads_transport_api/gtfsr.py
vicroads_transport_api-0.1.2.dist-info/LICENSE
vicroads_transport_api-0.1.2.dist-info/WHEEL
vicroads_transport_api-0.1.2.dist-info/METADATA
vicroads_transport_api-0.1.2.dist-info/RECORD
